Metadata-Version: 1.0
Name: Gauss-Binom-distributions-package
Version: 0.1
Summary: Gaussian and Binomial distributions
Home-page: UNKNOWN
Author: GHEORGHE ANDREI-ALEXANDRU
Author-email: andrei.gheorghe901@gmail.com
License: UNKNOWN
Platform: UNKNOWN
